convbot/__init__.py
convbot/__main__.py
convbot/convbot.py
convbot/force_async.py
LICENSE
convbot-0.1.1.dist-info/LICENSE
convbot-0.1.1.dist-info/WHEEL
convbot-0.1.1.dist-info/METADATA
convbot-0.1.1.dist-info/RECORD
